Metadata-Version: 2.3
Name: yta-ai-openai
Version: 0.0.1
Summary: Youtube Autonomous AI OpenAI Module.
Author: danialcala94
Author-email: danielalcalavalera@gmail.com
Requires-Python: ==3.9
Classifier: Programming Language :: Python :: 3
Classifier: Programming Language :: Python :: 3.9
Requires-Dist: openai (>=1.3.8,<9.0.0)
Requires-Dist: yta_constants (>=0.0.1,<1.0.0)
Requires-Dist: yta_file_downloader (>=0.0.1,<1.0.0)
Requires-Dist: yta_general (>=0.0.1,<1.0.0)
Requires-Dist: yta_programming (>=0.0.1,<1.0.0)
Requires-Dist: yta_validation (>=0.0.1,<1.0.0)
